README.md
setup.py
evidential_deep_learning/__init__.py
evidential_deep_learning.egg-info/PKG-INFO
evidential_deep_learning.egg-info/SOURCES.txt
evidential_deep_learning.egg-info/dependency_links.txt
evidential_deep_learning.egg-info/requires.txt
evidential_deep_learning.egg-info/top_level.txt
evidential_deep_learning/layers/__init__.py
evidential_deep_learning/layers/conv2d.py
evidential_deep_learning/layers/dense.py
evidential_deep_learning/losses/__init__.py
evidential_deep_learning/losses/continuous.py
evidential_deep_learning/losses/discrete.py