Metadata-Version: 2.1
Name: evidential-deep-learning
Version: 0.4.0
Summary: Learn fast, scalable, and calibrated measures of uncertainty using neural networks!
Home-page: https://github.com/aamini/evidential-deep-learning
Author: Alexander Amini
Author-email: amini@mit.edu
License: Apache License 2.0
Download-URL: https://github.com/aamini/evidential-deep-learning/archive/v0.4.0.tar.gz
Platform: UNKNOWN
Classifier: Programming Language :: Python
Classifier: Programming Language :: Python :: 3.7
Classifier: Operating System :: Unix
Classifier: Operating System :: Microsoft :: Windows
Classifier: Operating System :: MacOS
Classifier: Intended Audience :: Science/Research
Classifier: Topic :: Scientific/Engineering
Classifier: Topic :: Software Development
Requires-Python: >=3.7
